cate/__init__.py
cate/_svg.py
cate/check.py
cate/cli.py
cate/core.py
cate/export.py
cate/main.py
cate-1.1.dist-info/licenses/LICENSE.rst
cate-1.1.dist-info/METADATA
cate-1.1.dist-info/WHEEL
cate-1.1.dist-info/entry_points.txt
cate-1.1.dist-info/top_level.txt
cate-1.1.dist-info/RECORD
