Metadata-Version: 2.4
Name: cate
Version: 1.1
Summary: Tool to draw the templates of chaotic attractors
Maintainer-email: Raphaël Bleuse <cs@research.bleuse.net>
License-Expression: LGPL-3.0-only
Project-URL: homepage, https://gitlab.inria.fr/cate/cate
Project-URL: repository, https://gitlab.inria.fr/cate/cate.git
Project-URL: issues, https://gitlab.inria.fr/cate/cate/-/issues
Project-URL: changelog, https://gitlab.inria.fr/cate/cate/-/blob/master/Changelog.rst
Keywords: chaotic attractor,dynamical system,graph drawing,template
Classifier: Development Status :: 5 - Production/Stable
Classifier: Environment :: Console
Classifier: Intended Audience :: Science/Research
Classifier: Programming Language :: Python :: 3.10
Classifier: Programming Language :: Python :: 3.11
Classifier: Programming Language :: Python :: 3.12
Classifier: Programming Language :: Python :: 3.13
Classifier: Programming Language :: Python :: 3.14
Classifier: Topic :: Scientific/Engineering :: Mathematics
Classifier: Topic :: Scientific/Engineering :: Physics
Classifier: Topic :: Scientific/Engineering :: Visualization
Classifier: Topic :: Utilities
Requires-Python: >=3.10
License-File: LICENSE.rst
Requires-Dist: multiset==3.2.0
Requires-Dist: svgwrite==1.4.3
Dynamic: license-file
